[{"pk": 1, "model": "qi.catalog", "fields": {"code": "root", "create_date": "2013-05-22T14:25:55Z", "name": "\u6839\u76ee\u5f55", "parent": null, "state": "A", "modify_date": "2013-05-22T14:25:57Z", "ord": 0}}, {"pk": 2, "model": "qi.catalog", "fields": {"code": "root2", "create_date": "2013-05-22T14:29:16Z", "name": "\u76ee\u5f552", "parent": 1, "state": "A", "modify_date": "2013-05-22T14:29:17Z", "ord": 1}}, {"pk": 21, "model": "qi.catalog", "fields": {"code": "root3", "create_date": "2013-05-22T15:17:55Z", "name": "ddd", "parent": 1, "state": "A", "modify_date": "2013-05-22T15:17:57Z", "ord": 1}}]